CO224/Lab05/Part 3/alu.v
/*
    CO 224 : Lab 05 Part1
    ALU module
    E/16/069
*/

module alu(DATA1, DATA2, RESULT, SELECT);

    // port declaration
    input [7:0] DATA1, DATA2;
    input [2:0] SELECT;
    output reg [7:0] RESULT;

    // sensitive to changes of data1, data2 & select operands
    always @(DATA1, DATA2, SELECT)
    begin
        // select aluOperation
        case(SELECT)
            3'b000:     // loadi, mov
                #1 RESULT = DATA2 ; 
            3'b001:     // Addition
                #2 RESULT = DATA1 + DATA2 ; 
            3'b010:     // AND
                #1 RESULT = DATA1 & DATA2 ; 
            3'b011:     // OR
                #1 RESULT = DATA1 | DATA2 ; 
            default:    // unusesd bit combinations
                RESULT = 8'bxxxxxxxx ;                     
        endcase
    end
    
endmodule

CO224/Lab05/Part 1/testbench.v
/*
    CO 224 : Lab 05 Part1
    testbech for ALU module
    E/16/069
*/
module testbench;

    reg [7:0] OPERAND_1, OPERAND_2;
    reg [2:0] ALU_OP;
    wire [7:0] ALU_RESULT;

    alu myalu(OPERAND_1, OPERAND_2, ALU_RESULT, ALU_OP);

    initial
    begin
        $monitor($time, " OPERAND_1: %8b , OPERAND_2: %8b , ALU_RESULT: %8b , ALU_OP: %3b ", OPERAND_1, OPERAND_2,  ALU_RESULT, ALU_OP);
        $dumpfile("wavedata.vcd");
        $dumpvars(0, testbench);
    end

    initial
    begin

        // test "add" aluOp
        ALU_OP = 3'b001;
        OPERAND_1 = 8'b00001001;    
        OPERAND_2 = 8'b00010011 ;    
        //expected Result : 00011100  

        #10
        // test "load, mov" aluOp
        ALU_OP = 3'b000;
        //expected Result : 00010011  

        #10
        // test "AND" aluOp
        ALU_OP = 3'b010;
        OPERAND_1 = 8'b00010100;    
        OPERAND_2 = 8'b01011010;
        // expected Result : 00010000 

        #10
        // test "OR" aluOp
        ALU_OP = 3'b011;
        OPERAND_1 = 8'b00010100;    
        OPERAND_2 = 8'b01011010;
        // expected Result : 01011110 

        #10
        // test an unsused bit combination of aluOp
        ALU_OP = 3'b111;
        // expected Result : xxxxxxxx 

    end
endmodule

CO224/Lab05/Part 1/wavedata.vcd
$date
	Sun May  3 22:42:24 2020
$end
$version
	Icarus Verilog
$end
$timescale
	1s
$end
$scope module testbench $end
$var wire 8 ! ALU_RESULT [7:0] $end
$var reg 3 " ALU_OP [2:0] $end
$var reg 8 # OPERAND_1 [7:0] $end
$var reg 8 $ OPERAND_2 [7:0] $end
$scope module myalu $end
$var wire 8 % DATA1 [7:0] $end
$var wire 8 & DATA2 [7:0] $end
$var wire 3 ' SELECT [2:0] $end
$var reg 8 ( RESULT [7:0] $end
$upscope $end
$upscope $end
$enddefinitions $end
#0
$dumpvars
bx (
b1 '
b10011 &
b1001 %
b10011 $
b1001 #
b1 "
bx !
$end
#2
b11100 !
b11100 (
#10
b0 "
b0 '
#11
b10011 !
b10011 (
#20
b1011010 $
b1011010 &
b10100 #
b10100 %
b10 "
b10 '
#21
b10000 !
b10000 (
#30
b11 "
b11 '
#31
b1011110 !
b1011110 (
#40
bx !
bx (
b111 "
b111 '
